{
    "out": "../../docs/sdk/",
    "exclude": ["**/node_modules/**", "**/tests/**"],
    "navigationLinks": {
        "Discord": "https://discord.gg/smythos",
        "Core": "https://smythos.github.io/sre/core/",
        "SDK": "https://smythos.github.io/sre/sdk/",
        "CLI": "https://smythos.github.io/sre/cli/",
        "GitHub": "https://github.com/smythos/sre"
    },
    "plugin": ["./scripts/typedoc-header-plugin.cjs"],
    "customCss": "./docs/assets/custom.css",

    "projectDocuments": ["./docs/**/*.md"],
    "name": "SmythOS SDK",

    "entryPoints": ["./src/index.ts"],
    "entryPointStrategy": "expand"
}
